mediapipe_model_maker/__init__.py
mediapipe_model_maker/python/__init__.py
mediapipe_model_maker/python/core/__init__.py
mediapipe_model_maker/python/core/hyperparameters.py
mediapipe_model_maker/python/core/data/__init__.py
mediapipe_model_maker/python/core/data/cache_files.py
mediapipe_model_maker/python/core/data/classification_dataset.py
mediapipe_model_maker/python/core/data/data_util.py
mediapipe_model_maker/python/core/data/dataset.py
mediapipe_model_maker/python/core/tasks/__init__.py
mediapipe_model_maker/python/core/tasks/classifier.py
mediapipe_model_maker/python/core/tasks/custom_model.py
mediapipe_model_maker/python/core/utils/__init__.py
mediapipe_model_maker/python/core/utils/file_util.py
mediapipe_model_maker/python/core/utils/hub_loader.py
mediapipe_model_maker/python/core/utils/loss_functions.py
mediapipe_model_maker/python/core/utils/metrics.py
mediapipe_model_maker/python/core/utils/model_util.py
mediapipe_model_maker/python/core/utils/quantization.py
mediapipe_model_maker/python/core/utils/test_util.py
mediapipe_model_maker/python/text/__init__.py
mediapipe_model_maker/python/text/core/__init__.py
mediapipe_model_maker/python/text/core/bert_model_options.py
mediapipe_model_maker/python/text/core/bert_model_spec.py
mediapipe_model_maker/python/text/text_classifier/__init__.py
mediapipe_model_maker/python/text/text_classifier/bert_tokenizer.py
mediapipe_model_maker/python/text/text_classifier/dataset.py
mediapipe_model_maker/python/text/text_classifier/hyperparameters.py
mediapipe_model_maker/python/text/text_classifier/model_options.py
mediapipe_model_maker/python/text/text_classifier/model_spec.py
mediapipe_model_maker/python/text/text_classifier/model_with_tokenizer.py
mediapipe_model_maker/python/text/text_classifier/preprocessor.py
mediapipe_model_maker/python/text/text_classifier/text_classifier.py
mediapipe_model_maker/python/text/text_classifier/text_classifier_demo.py
mediapipe_model_maker-0.2.1.4.dist-info/METADATA
mediapipe_model_maker-0.2.1.4.dist-info/WHEEL
mediapipe_model_maker-0.2.1.4.dist-info/top_level.txt
mediapipe_model_maker-0.2.1.4.dist-info/RECORD
